README.rst
setup.py
JMRPi.Spark.egg-info/PKG-INFO
JMRPi.Spark.egg-info/SOURCES.txt
JMRPi.Spark.egg-info/dependency_links.txt
JMRPi.Spark.egg-info/top_level.txt
JMRPiSpark/__init__.py
JMRPiSpark/Drives/__init__.py
JMRPiSpark/Drives/Attitude/MPU6050.py
JMRPiSpark/Drives/Attitude/__init__.py
JMRPiSpark/Drives/Audio/RPiAudio.py
JMRPiSpark/Drives/Audio/RPiTone.py
JMRPiSpark/Drives/Audio/__init__.py
JMRPiSpark/Drives/Display/RPiDisplay.py
JMRPiSpark/Drives/Display/SSD1306.py
JMRPiSpark/Drives/Display/__init__.py
JMRPiSpark/Drives/Key/RPiKeyButtons.py
JMRPiSpark/Drives/Key/__init__.py
JMRPiSpark/Drives/Screen/SSPILScreen.py
JMRPiSpark/Drives/Screen/SScreen.py
JMRPiSpark/Drives/Screen/SScreenILI9341.py
JMRPiSpark/Drives/Screen/SScreenSSD1306.py
JMRPiSpark/Drives/Screen/__init__.py